setup.py
snapext/__init__.py
snapext.egg-info/PKG-INFO
snapext.egg-info/SOURCES.txt
snapext.egg-info/dependency_links.txt
snapext.egg-info/top_level.txt