Metadata-Version: 1.1
Name: snapext
Version: 0.1.1
Summary: Server for writing Snap! extensions
Home-page: https://github.com/blob8108/snapext
Author: Tim Radvan
Author-email: blob8108@gmail.com
License: MIT
Platform: UNKNOWN
Classifier: Programming Language :: Python
